MANIFEST.in
README.txt
setup.py
djero/__init__.py
djero/admin.py
djero/forms.py
djero/managers.py
djero/models.py
djero/search_indexes.py
djero/signals.py
djero/sitemap.py
djero/tests.py
djero/urls.py
djero/views.py
djero.egg-info/PKG-INFO
djero.egg-info/SOURCES.txt
djero.egg-info/dependency_links.txt
djero.egg-info/not-zip-safe
djero.egg-info/top_level.txt
djero/templates/forum/_nav.html
djero/templates/forum/base.html
djero/templates/forum/category.html
djero/templates/forum/create_topic.html
djero/templates/forum/edit_topic.html
djero/templates/forum/forum.html
djero/templates/forum/index.html
djero/templates/forum/reply.html
djero/templates/forum/topic.html
djero/templates/search/indexes/djero/message_text.txt
djero/templates/search/indexes/djero/topic_text.txt
djero/templates/search/indexes/message/topic_text.txt
djero/templatetags/__init__.py
djero/templatetags/forum_tags.py